QuickSync4Linux/__init__.py
QuickSync4Linux/__main__.py
QuickSync4Linux/at.py
QuickSync4Linux/obex.py
QuickSync4Linux/quicksync.py
quicksync4linux-1.0.dist-info/METADATA
quicksync4linux-1.0.dist-info/WHEEL
quicksync4linux-1.0.dist-info/entry_points.txt
quicksync4linux-1.0.dist-info/licenses/LICENSE.txt
quicksync4linux-1.0.dist-info/RECORD
