Metadata-Version: 2.3
Name: QuickSync4Linux
Version: 1.0
Summary: Gigaset QuickSync for Linux
Project-URL: Homepage, https://github.com/schorschii/QuickSync4Linux
Project-URL: Issues, https://github.com/schorschii/QuickSync4Linux/issues
Author: https://github.com/schorschii
License: GNU GENERAL PUBLIC LICENSE
License-File: LICENSE.txt
Requires-Python: >=3.7
Requires-Dist: pyserial
